[
  {
    "name": "covers",
    "type": "directory",
    "category": "root",
    "children": [
      {
        "name": "bestie-covers.jpg",
        "type": "image",
        "thumbnail": "/assets/covers/bestie-covers.jpg",
        "category": "covers"
      },
      {
        "name": "ik-voel-niks-covers.jpg",
        "type": "image",
        "thumbnail": "/assets/covers/ik-voel-niks-covers.jpg",
        "category": "covers"
      },
      {
        "name": "luxe-problemen-covers.jpg",
        "type": "image",
        "thumbnail": "/assets/covers/luxe-problemen-covers.jpg",
        "category": "covers"
      },
      {
        "name": "moeilijk-covers.jpg",
        "type": "image",
        "thumbnail": "/assets/covers/moeilijk-covers.jpg",
        "category": "covers"
      }
    ]
  },
  {
    "name": "lyrics",
    "type": "directory",
    "category": "root",
    "children": [
      {
        "name": "bestie-lyrics.md",
        "type": "text",
        "thumbnail": "/assets/covers/bestie-covers.jpg",
        "category": "lyrics"
      },
      {
        "name": "ik-voel-niks-lyrics.md",
        "type": "text",
        "thumbnail": "/assets/covers/ik-voel-niks-covers.jpg",
        "category": "lyrics"
      },
      {
        "name": "luxe-problemen-lyrics.md",
        "type": "text",
        "thumbnail": "/assets/covers/luxe-problemen-covers.jpg",
        "category": "lyrics"
      },
      {
        "name": "moeilijk-lyrics.md",
        "type": "text",
        "thumbnail": "/assets/covers/moeilijk-covers.jpg",
        "category": "lyrics"
      }
    ]
  },
  {
    "name": "posters",
    "type": "directory",
    "category": "root",
    "children": [
      {
        "name": "moeilijk-poster.png",
        "type": "image",
        "thumbnail": "/assets/posters/moeilijk-poster.png",
        "category": "posters"
      }
    ]
  },
  {
    "name": "press",
    "type": "directory",
    "category": "root",
    "children": [
      {
        "name": "ayisha-1-portrait.jpg",
        "type": "image",
        "thumbnail": "/assets/press/ayisha-1-portrait.jpg",
        "category": "press"
      },
      {
        "name": "ayisha-2-portrait.jpg",
        "type": "image",
        "thumbnail": "/assets/press/ayisha-2-portrait.jpg",
        "category": "press"
      },
      {
        "name": "ayisha-portrait.jpg",
        "type": "image",
        "thumbnail": "/assets/press/ayisha-portrait.jpg",
        "category": "press"
      },
      {
        "name": "betty-1-portrait.jpg",
        "type": "image",
        "thumbnail": "/assets/press/betty-1-portrait.jpg",
        "category": "press"
      },
      {
        "name": "betty-portrait.jpg",
        "type": "image",
        "thumbnail": "/assets/press/betty-portrait.jpg",
        "category": "press"
      },
      {
        "name": "duo-portrait.png",
        "type": "image",
        "thumbnail": "/assets/press/duo-portrait.png",
        "category": "press"
      },
      {
        "name": "logo.png",
        "type": "image",
        "thumbnail": "/assets/press/logo.png",
        "category": "press"
      },
      {
        "name": "song-pack",
        "type": "directory",
        "category": "press",
        "children": [
          {
            "name": "bestie",
            "type": "directory",
            "category": "press",
            "children": [
              {
                "name": "Bestie cover fv.jpg",
                "type": "image",
                "thumbnail": "/assets/press/song-pack/bestie/Bestie cover fv.jpg",
                "category": "press"
              },
              {
                "name": "bestie-womance-1.png",
                "type": "image",
                "thumbnail": "/assets/press/song-pack/bestie/bestie-womance-1.png",
                "category": "press"
              },
              {
                "name": "bestie-womance-10.png",
                "type": "image",
                "thumbnail": "/assets/press/song-pack/bestie/bestie-womance-10.png",
                "category": "press"
              },
              {
                "name": "bestie-womance-2.png",
                "type": "image",
                "thumbnail": "/assets/press/song-pack/bestie/bestie-womance-2.png",
                "category": "press"
              },
              {
                "name": "bestie-womance-3.png",
                "type": "image",
                "thumbnail": "/assets/press/song-pack/bestie/bestie-womance-3.png",
                "category": "press"
              },
              {
                "name": "bestie-womance-4.png",
                "type": "image",
                "thumbnail": "/assets/press/song-pack/bestie/bestie-womance-4.png",
                "category": "press"
              },
              {
                "name": "bestie-womance-5.png",
                "type": "image",
                "thumbnail": "/assets/press/song-pack/bestie/bestie-womance-5.png",
                "category": "press"
              },
              {
                "name": "bestie-womance-6.png",
                "type": "image",
                "thumbnail": "/assets/press/song-pack/bestie/bestie-womance-6.png",
                "category": "press"
              },
              {
                "name": "bestie-womance-7.png",
                "type": "image",
                "thumbnail": "/assets/press/song-pack/bestie/bestie-womance-7.png",
                "category": "press"
              },
              {
                "name": "bestie-womance-8.png",
                "type": "image",
                "thumbnail": "/assets/press/song-pack/bestie/bestie-womance-8.png",
                "category": "press"
              },
              {
                "name": "bestie-womance-9.png",
                "type": "image",
                "thumbnail": "/assets/press/song-pack/bestie/bestie-womance-9.png",
                "category": "press"
              },
              {
                "name": "bestie-womance.png",
                "type": "image",
                "thumbnail": "/assets/press/song-pack/bestie/bestie-womance.png",
                "category": "press"
              },
              {
                "name": "hand-ayi.png",
                "type": "image",
                "thumbnail": "/assets/press/song-pack/bestie/hand-ayi.png",
                "category": "press"
              },
              {
                "name": "hand-bet.png",
                "type": "image",
                "thumbnail": "/assets/press/song-pack/bestie/hand-bet.png",
                "category": "press"
              },
              {
                "name": "yt-bestie-banner.jpg",
                "type": "image",
                "thumbnail": "/assets/press/song-pack/bestie/yt-bestie-banner.jpg",
                "category": "press"
              }
            ]
          },
          {
            "name": "ik-voel-niks",
            "type": "directory",
            "category": "press",
            "children": [
              {
                "name": "Ik voel niks stars .jpg",
                "type": "image",
                "thumbnail": "/assets/press/song-pack/ik-voel-niks/Ik voel niks stars .jpg",
                "category": "press"
              },
              {
                "name": "InShot_20250107_170043637.png",
                "type": "image",
                "thumbnail": "/assets/press/song-pack/ik-voel-niks/InShot_20250107_170043637.png",
                "category": "press"
              },
              {
                "name": "Womance - Ik Voel Niks cover.jpg",
                "type": "image",
                "thumbnail": "/assets/press/song-pack/ik-voel-niks/Womance - Ik Voel Niks cover.jpg",
                "category": "press"
              },
              {
                "name": "Womance profiel foto.jpg",
                "type": "image",
                "thumbnail": "/assets/press/song-pack/ik-voel-niks/Womance profiel foto.jpg",
                "category": "press"
              },
              {
                "name": "YT-Thumbnail-Ik voel niks.png",
                "type": "image",
                "thumbnail": "/assets/press/song-pack/ik-voel-niks/YT-Thumbnail-Ik voel niks.png",
                "category": "press"
              }
            ]
          },
          {
            "name": "luxe-problemen",
            "type": "directory",
            "category": "press",
            "children": [
              {
                "name": "Betty KO1.png",
                "type": "image",
                "thumbnail": "/assets/press/song-pack/luxe-problemen/Betty KO1.png",
                "category": "press"
              },
              {
                "name": "Doakes.png",
                "type": "image",
                "thumbnail": "/assets/press/song-pack/luxe-problemen/Doakes.png",
                "category": "press"
              },
              {
                "name": "Luxe Problemen - Coverart Final.jpg",
                "type": "image",
                "thumbnail": "/assets/press/song-pack/luxe-problemen/Luxe Problemen - Coverart Final.jpg",
                "category": "press"
              },
              {
                "name": "Luxe Problemen Titel.png",
                "type": "image",
                "thumbnail": "/assets/press/song-pack/luxe-problemen/Luxe Problemen Titel.png",
                "category": "press"
              },
              {
                "name": "SUB-Herken je het ook.png",
                "type": "image",
                "thumbnail": "/assets/press/song-pack/luxe-problemen/SUB-Herken je het ook.png",
                "category": "press"
              },
              {
                "name": "koppelpoort-shot-ab.png",
                "type": "image",
                "thumbnail": "/assets/press/song-pack/luxe-problemen/koppelpoort-shot-ab.png",
                "category": "press"
              },
              {
                "name": "mc-shot-ab.png",
                "type": "image",
                "thumbnail": "/assets/press/song-pack/luxe-problemen/mc-shot-ab.png",
                "category": "press"
              },
              {
                "name": "sad op bankje-shot.png",
                "type": "image",
                "thumbnail": "/assets/press/song-pack/luxe-problemen/sad op bankje-shot.png",
                "category": "press"
              },
              {
                "name": "stadsmuur-shot-ab-1.png",
                "type": "image",
                "thumbnail": "/assets/press/song-pack/luxe-problemen/stadsmuur-shot-ab-1.png",
                "category": "press"
              },
              {
                "name": "stadsmuur-shot-ab.png",
                "type": "image",
                "thumbnail": "/assets/press/song-pack/luxe-problemen/stadsmuur-shot-ab.png",
                "category": "press"
              },
              {
                "name": "timbs-shot.png",
                "type": "image",
                "thumbnail": "/assets/press/song-pack/luxe-problemen/timbs-shot.png",
                "category": "press"
              },
              {
                "name": "tower-ayi-shot.png",
                "type": "image",
                "thumbnail": "/assets/press/song-pack/luxe-problemen/tower-ayi-shot.png",
                "category": "press"
              },
              {
                "name": "tower-bat-shot.png",
                "type": "image",
                "thumbnail": "/assets/press/song-pack/luxe-problemen/tower-bat-shot.png",
                "category": "press"
              },
              {
                "name": "wijn-shot.png",
                "type": "image",
                "thumbnail": "/assets/press/song-pack/luxe-problemen/wijn-shot.png",
                "category": "press"
              },
              {
                "name": "womance armedillo shot4.png",
                "type": "image",
                "thumbnail": "/assets/press/song-pack/luxe-problemen/womance armedillo shot4.png",
                "category": "press"
              },
              {
                "name": "womance bankje-shot.png",
                "type": "image",
                "thumbnail": "/assets/press/song-pack/luxe-problemen/womance bankje-shot.png",
                "category": "press"
              },
              {
                "name": "womance bankje-shot1.png",
                "type": "image",
                "thumbnail": "/assets/press/song-pack/luxe-problemen/womance bankje-shot1.png",
                "category": "press"
              },
              {
                "name": "womance bankje-shot2.png",
                "type": "image",
                "thumbnail": "/assets/press/song-pack/luxe-problemen/womance bankje-shot2.png",
                "category": "press"
              },
              {
                "name": "womance bankje-shot3.png",
                "type": "image",
                "thumbnail": "/assets/press/song-pack/luxe-problemen/womance bankje-shot3.png",
                "category": "press"
              },
              {
                "name": "womance shot.png",
                "type": "image",
                "thumbnail": "/assets/press/song-pack/luxe-problemen/womance shot.png",
                "category": "press"
              },
              {
                "name": "womance w shot.png",
                "type": "image",
                "thumbnail": "/assets/press/song-pack/luxe-problemen/womance w shot.png",
                "category": "press"
              }
            ]
          },
          {
            "name": "moeilijk",
            "type": "directory",
            "category": "press",
            "children": [
              {
                "name": "Ayi moeilijk.png",
                "type": "image",
                "thumbnail": "/assets/press/song-pack/moeilijk/Ayi moeilijk.png",
                "category": "press"
              },
              {
                "name": "Betty moeilijk.png",
                "type": "image",
                "thumbnail": "/assets/press/song-pack/moeilijk/Betty moeilijk.png",
                "category": "press"
              },
              {
                "name": "Hak womance.png",
                "type": "image",
                "thumbnail": "/assets/press/song-pack/moeilijk/Hak womance.png",
                "category": "press"
              },
              {
                "name": "aankondiging Moeilijk.png",
                "type": "image",
                "thumbnail": "/assets/press/song-pack/moeilijk/aankondiging Moeilijk.png",
                "category": "press"
              },
              {
                "name": "cover-moeilijk.jpg",
                "type": "image",
                "thumbnail": "/assets/press/song-pack/moeilijk/cover-moeilijk.jpg",
                "category": "press"
              },
              {
                "name": "cover-moeilijk.png",
                "type": "image",
                "thumbnail": "/assets/press/song-pack/moeilijk/cover-moeilijk.png",
                "category": "press"
              },
              {
                "name": "poster-moeilijk (2).png",
                "type": "image",
                "thumbnail": "/assets/press/song-pack/moeilijk/poster-moeilijk (2).png",
                "category": "press"
              },
              {
                "name": "poster-moeilijk.png",
                "type": "image",
                "thumbnail": "/assets/press/song-pack/moeilijk/poster-moeilijk.png",
                "category": "press"
              },
              {
                "name": "postit.png",
                "type": "image",
                "thumbnail": "/assets/press/song-pack/moeilijk/postit.png",
                "category": "press"
              },
              {
                "name": "yt-thumbnail.png",
                "type": "image",
                "thumbnail": "/assets/press/song-pack/moeilijk/yt-thumbnail.png",
                "category": "press"
              }
            ]
          }
        ]
      }
    ]
  },
  {
    "name": "songs",
    "type": "directory",
    "category": "root",
    "children": [
      {
        "name": "bestie-songs.mp3",
        "type": "audio",
        "thumbnail": "/assets/covers/bestie-covers.jpg",
        "category": "songs"
      },
      {
        "name": "ik-voel-niks-songs.mp3",
        "type": "audio",
        "thumbnail": "/assets/covers/ik-voel-niks-covers.jpg",
        "category": "songs"
      },
      {
        "name": "luxe-problemen-songs.mp3",
        "type": "audio",
        "thumbnail": "/assets/covers/luxe-problemen-covers.jpg",
        "category": "songs"
      },
      {
        "name": "moeilijk-songs.mp3",
        "type": "audio",
        "thumbnail": "/assets/covers/moeilijk-covers.jpg",
        "category": "songs"
      }
    ]
  }
]